polytext/__init__.py
polytext/converter/__init__.py
polytext/converter/audio_to_text.py
polytext/converter/base.py
polytext/converter/document_ocr_to_text.py
polytext/converter/html_to_md.py
polytext/converter/md_to_text.py
polytext/converter/ocr_to_text.py
polytext/converter/pdf.py
polytext/converter/text_to_md.py
polytext/converter/video_to_audio.py
polytext/exceptions/__init__.py
polytext/exceptions/base.py
polytext/generator/__init__.py
polytext/generator/pdf.py
polytext/loader/__init__.py
polytext/loader/audio.py
polytext/loader/base.py
polytext/loader/document.py
polytext/loader/document_ocr.py
polytext/loader/html.py
polytext/loader/markdown.py
polytext/loader/ocr.py
polytext/loader/plain_text.py
polytext/loader/video.py
polytext/loader/youtube.py
polytext/loader/youtube_llm.py
polytext/loader/downloader/__init__.py
polytext/loader/downloader/downloader.py
polytext/processor/__init__.py
polytext/processor/audio_chunker.py
polytext/processor/text_merger.py
polytext/processor/transcript_chunker.py
polytext/prompts/__init__.py
polytext/prompts/ocr.py
polytext/prompts/text_merging.py
polytext/prompts/text_to_md.py
polytext/prompts/transcription.py
polytext/utils/__init__.py
polytext/utils/utils.py
polytext-0.1.4.dist-info/licenses/LICENSE
polytext-0.1.4.dist-info/METADATA
polytext-0.1.4.dist-info/WHEEL
polytext-0.1.4.dist-info/top_level.txt
polytext-0.1.4.dist-info/RECORD
