Metadata-Version: 2.4
Name: polytext
Version: 0.1.4
Summary: Python utilities to simplify document files management
Home-page: https://github.com/docsity/polytext
Author: Matteo Senardi
Author-email: matteo.s@docsity.com
License: MIT
Classifier: License :: OSI Approved :: MIT License
Classifier: Operating System :: OS Independent
Classifier: Programming Language :: Python :: 3.12
Classifier: Programming Language :: Python :: 3.13
Classifier: Topic :: Software Development :: Libraries :: Application Frameworks
Classifier: Topic :: Software Development :: Libraries :: Python Modules
Requires-Python: >=3.12
License-File: LICENSE
Requires-Dist: pypdf==5.5.0
Requires-Dist: PyMuPDF>=1.25.5
Requires-Dist: pycryptodome==3.23.0
Requires-Dist: weasyprint==65.1
Requires-Dist: markdown==3.8
Requires-Dist: python-docx==1.1.2
Requires-Dist: google-api-core>=2.24.2
Requires-Dist: google-cloud-storage<3.0.0,>=2.17
Requires-Dist: google-genai>=1.16.1
Requires-Dist: boto3>=1.38.19
Requires-Dist: botocore>=1.18.19
Requires-Dist: ffmpeg-python==0.2.0
Requires-Dist: pydub==0.25.1
Requires-Dist: youtube-transcript-api==1.0.3
Requires-Dist: yt-dlp==2025.5.22
Requires-Dist: charset-normalizer==3.4.2
Requires-Dist: requests==2.32.3
Requires-Dist: markitdown[all]==0.1.1
Requires-Dist: pymupdf4llm==0.0.24
Requires-Dist: html2text==2025.4.15
Requires-Dist: pathlib==1.0.1
Requires-Dist: retry==0.9.2
Provides-Extra: sentry
Requires-Dist: sentry-sdk==2.29.1; extra == "sentry"
Dynamic: author
Dynamic: author-email
Dynamic: classifier
Dynamic: description
Dynamic: description-content-type
Dynamic: home-page
Dynamic: license
Dynamic: license-file
Dynamic: provides-extra
Dynamic: requires-dist
Dynamic: requires-python
Dynamic: summary
